odoo10_addon_partner_company_type-10.0.1.0.1-py2.7-nspkg.pth
odoo/addons/partner_company_type/README.rst
odoo/addons/partner_company_type/__init__.py
odoo/addons/partner_company_type/__manifest__.py
odoo/addons/partner_company_type/demo/res_partner_company_type.xml
odoo/addons/partner_company_type/migrations/10.0.1.0.1/post-migration.py
odoo/addons/partner_company_type/models/__init__.py
odoo/addons/partner_company_type/models/res_partner.py
odoo/addons/partner_company_type/models/res_partner_company_type.py
odoo/addons/partner_company_type/security/res_partner_company_type.xml
odoo/addons/partner_company_type/static/description/icon.png
odoo/addons/partner_company_type/tests/__init__.py
odoo/addons/partner_company_type/tests/test_company_type.py
odoo/addons/partner_company_type/views/res_partner.xml
odoo/addons/partner_company_type/views/res_partner_company_type.xml
odoo10_addon_partner_company_type-10.0.1.0.1.dist-info/DESCRIPTION.rst
odoo10_addon_partner_company_type-10.0.1.0.1.dist-info/METADATA
odoo10_addon_partner_company_type-10.0.1.0.1.dist-info/RECORD
odoo10_addon_partner_company_type-10.0.1.0.1.dist-info/WHEEL
odoo10_addon_partner_company_type-10.0.1.0.1.dist-info/metadata.json
odoo10_addon_partner_company_type-10.0.1.0.1.dist-info/namespace_packages.txt
odoo10_addon_partner_company_type-10.0.1.0.1.dist-info/top_level.txt
